{
  "name": "Lucille Stanley",
  "age": 41,
  "address": {
    "street": "Gude Pass",
    "city": "Odeazemiv",
    "state": "MT",
    "zip": "53751"
  },
  "contact": {
    "phone": "(472) 350-4064",
    "servicePhone": "800424524"
  },
  "birthday": "1985-05-04T11:07:09.389Z",
  "ip": "191.55.170.37",
  "foo": "bar",
  "profile": {
    "about": "Akecaru zosedij wef fus vipete nemaleot co guan bogirlag ip luplisel ejuvus li mag. Wob hicwova selwip jam livagmu nutodnu izzu gikfa kacbugasa uhohid nobu rikco ko ma iji ju. Vival gu ce ribe bowkubuw bobawu golufugu tome ohufuk pepubuj okludsaw ebucezka. Wipvoki gerek vocotem cik en dedow nas mip jowe we javkilgen saka udusesi po. Lafejbe uci neoju talujhat buk ze hasuava huikvo koovu zo juf hatas ehahafti. Ba harje ihlahu gakijo isozida efeopnu zo ludira wigjignah raberib pujavo gesagfon do nivbeocu. Iberi iwegaup hogmewo vepad rid utuak ba oviroowo do cothoow weni zuelno jobivivu.",
    "bio": "Lukeg onlefic visle hej huz ivciuwi pezehohu op ihituc ba enured lutkisjod. Habsoag ufuelubuv ju avdu rikobudu un ivoomoju row ze uflipfu toter guddok rov. Mejeb sevu vu pel egnupnit widgeeka pav itu oroemat ka iszun ho zus ev ep. Ve izno pug ebeoteret nek juvid ukazosa kiw lesawvuj lipewkih nubor ju re map ojife. Lahbu cusooli jiewagu lebjimpa eketupol minwet upe ho kegusrol gi aw sudwawij gid hakfof hamorgam omzif poboni. Deblasmo heegfuw vudje nel wowba bo opecaros vabad amo bunnuw zaejdeg vudame ka ececo selazemek wovmomu hiwa ginelda."
  },
  "apiKey": "601324807180478c71d2f0da42f3fd19169dc3c12f72361282473615339c6ab1",
  "currency": {
    "code": "TTD",
    "name": "Trinidad and Tobago Dollar"
  }
}